{
  "name": "Barntar",
  "pantheon": "Storm",
  "source": "CultOnePagers2019/Storm/Barntar.pdf",
  "sourceVersion": "2019 edition v5.2",
  "subtitle": "Orlanthi Ploughman God",
  "runes": [],
  "requirements": {
    "initiate": "to have 5 cult skills at 50%+ one of which needs to be Cult Runic Affinity, Examiners need to be convinced at 3 of them.",
    "runelord": "to have 3"
  },
  "cultSkills": [
    "First Aid",
    "Lore (Farming)",
    "Lore (Cult)",
    "Combat Style (Spear)",
    "Drive",
    "Runic Affinity",
    "Craft (Farming)"
  ],
  "folkMagic": [
    "Bladesharp",
    "Heal",
    "Might",
    "Preserve",
    "Repair",
    "Vigour",
    "Warmth"
  ],
  "miracles": {
    "initiate": [
      "Command (Specific Species, Monster or Spirit)",
      "Extension",
      "Find (Specific Thing)",
      "Chastise",
      "Divination"
    ],
    "associate": [
      "Ernalda:Bless Crops",
      "Orlanth:Shield"
    ],
    "runelord": [
      "Excommunication",
      "Mindlink",
      "Summon Spirit of Reprisal",
      "Sanctify"
    ]
  },
  "personalityTraits": [
    "Adventurous",
    "Dynamic",
    "Impulsive",
    "Reckless",
    "Energetic",
    "Rebellious",
    "Passionate",
    "Proud",
    "Unpredictable"
  ],
  "enemyCults": [],
  "hostileCults": [],
  "friendlyCults": [],
  "associatedCults": [],
  "areas": [
    "Coastal Pamaltela",
    "Dragon Pass",
    "East",
    "Fonrit",
    "Holy Country",
    "Lunar",
    "Oceans",
    "West"
  ],
  "holyDays": [
    "Sea/Harmony/Winds"
  ],
  "spiritSocieties": [],
  "oppositeRune": "Stasis"
}
